{
    "id": 3305,
    "project_name": "Frosties",
    "title": "Frosties",
    "description": "<p dir=\"ltr\" style=\"line-height:1.38;background-color:#ffffff;margin-top:0pt;margin-bottom:0pt;\"><span style=\"font-size:10.5pt;font-family:Arial;color:#373f47;background-color:#f5f8ff;font-weight:700;font-style:normal;font-variant:normal;text-decoration:none;vertical-align:baseline;white-space:pre;white-space:pre-wrap;\"><strong>Quick Summary</strong></span></p><p dir=\"ltr\" style=\"line-height:1.38;background-color:#ffffff;margin-top:0pt;margin-bottom:0pt;\"><span style=\"font-size:12pt;font-family:Roboto,sans-serif;color:#292929;background-color:#ffffff;font-weight:400;font-style:normal;font-variant:normal;text-decoration:none;vertical-align:baseline;white-space:pre;white-space:pre-wrap;\">The developers of the Frosties NFT collection sold 8,888 tokens with a floor price of 0.04 ETH and disappeared. Their social accounts were immediately deactivated.</span></p><p dir=\"ltr\" style=\"line-height:1.38;background-color:#ffffff;margin-top:0pt;margin-bottom:0pt;\"><span style=\"font-size:12pt;font-family:Roboto,sans-serif;color:#292929;background-color:#ffffff;font-weight:400;font-style:normal;font-variant:normal;text-decoration:none;vertical-align:baseline;white-space:pre;white-space:pre-wrap;\">The token price fell to zero.&nbsp;</span></p>",
    "name_categories": "NFT",
    "token_name": "FROST",
    "proof_archive_link": null,
    "technical_issue": null,
    "token_address": "0x3C99F2A4b366D46bcf2277639A135A6D1288EcEB",
    "token_addresses": [
        {
            "address": "0x3C99F2A4b366D46bcf2277639A135A6D1288EcEB",
            "url": null,
            "network": {
                "id": 1,
                "icon_link": "safe/files/network/involved/ethereum.svg"
            }
        }
    ],
    "logo_link": "safe/files/scamDatabase/logo/63b35122287d0.png",
    "date": "2022-1-9",
    "scam_updates": [],
    "proof_link": "https://markets.businessinsider.com/news/currencies/nft-frosties-rug-pull-crypto-discord-opensea-non-fungible-tokens-2022-1",
    "website_link": "https://frosties.io/",
    "webarchive_link": "https://archive.ph/RvyTA",
    "twitter_link": null,
    "telegram_link": null,
    "our_post_link": null,
    "funds_lost": 1300000,
    "funds_returned": 0,
    "funds_by_chains": [],
    "funds_recovered": null,
    "active": 1,
    "git_hub": null,
    "git_hub_contract_link": null,
    "discord": null,
    "bug_bounty_program_link": null,
    "bug_bounty_program_company": null,
    "audit_code_conf": 0,
    "is_verified_source_code": 1,
    "is_public_team": 0,
    "scam_type": {
        "id": 5,
        "type": "Abandoned"
    },
    "network": {},
    "scamNetworks": [
        {
            "networks_id": 1,
            "scam_database_id": 3305,
            "networks": {
                "id": 1,
                "name": "Ethereum",
                "icon_link": "safe/files/network/ethereum.png"
            }
        }
    ],
    "auditedBy": []
}