{
    "id": 2605,
    "project_name": "Golden Bar Farm",
    "title": "Golden Bar Farm",
    "description": null,
    "name_categories": "Yield Aggregator",
    "token_name": "GOLD",
    "proof_archive_link": null,
    "technical_issue": null,
    "token_address": "0xdEC72bbC3365646fE0267fC08Cd05F79C4Be0060",
    "token_addresses": [],
    "logo_link": "safe/files/scamDatabase/logo/613203e0bf1f1.png",
    "date": "2021-9-3",
    "scam_updates": [],
    "proof_link": "https://bscscan.com/token/0xdEC72bbC3365646fE0267fC08Cd05F79C4Be0060?a=0x71fad8aa358c866c1af8637ac034a8869192dc72",
    "website_link": "https://goldbar.farm",
    "webarchive_link": null,
    "twitter_link": null,
    "telegram_link": null,
    "our_post_link": null,
    "funds_lost": 0,
    "funds_returned": 0,
    "funds_by_chains": [],
    "funds_recovered": null,
    "active": 1,
    "git_hub": null,
    "git_hub_contract_link": null,
    "discord": null,
    "bug_bounty_program_link": null,
    "bug_bounty_program_company": null,
    "audit_code_conf": null,
    "is_verified_source_code": null,
    "is_public_team": null,
    "scam_type": {
        "id": 10,
        "type": "Rugpull"
    },
    "network": {},
    "scamNetworks": [
        {
            "networks_id": 56,
            "scam_database_id": 2605,
            "networks": {
                "id": 56,
                "name": "Binance",
                "icon_link": "safe/files/network/bsc.png"
            }
        }
    ],
    "auditedBy": []
}