{
    "id": 2553,
    "project_name": "THORChain",
    "title": "THORChain (2)",
    "description": "<p><strong>Quick Summary</strong></p><p>Thorchain Bifrost component was exploited through the ETH Router contract, resulting in the loss of various tokens including 966.62 ALCX, 20,866,664.53 XRUNE, 1,672,794.010 USDC, 56,104 SUSHI, 6.91 YFI, and 990,137.46 USDT.</p><p><br></p><p><strong>Details of the Exploit</strong></p><p>The attacker created a fake router and emitted a deposit event by sending ETH. They then passed returnVaultAssets() with a small amount of ETH, but the router was defined as an Asgard vault. On the Thorchain Router, it forwarded ETH to the fake Asgard. This action created a fake deposit event with a malicious memo. Thorchain Bifrost interpreted this as a normal deposit and refunded to the attacker due to a bad memo definition.</p><p><strong><br></strong></p><p><strong>Block Data Reference</strong></p><p><br></p><p>The attacker's address:</p><p>https://etherscan.io/address/0xd95e6eab231b9f3afa24c31c7050bd84c2982072#tokentxns</p><p><br></p><p>The transaction behind the attack:</p><p>https://etherscan.io/tx/0x9db403ad39d3fe78de378af0b49f03d244326662f7fee230db87d12a624f564b</p><p><br></p><p>Other relevant addresses:</p><p>Router: https://etherscan.io/address/0xc145990e84155416144c532e31f89b840ca8c2ce</p><p>Vault: https://etherscan.io/address/0xf56cba49337a624e94042e325ad6bc864436e370</p><p>Attack contract: https://etherscan.io/address/0x700196e226283671a3de6704ebcdb37a76658805</p><p>Attack wallet (spawned from Tornado Cash): https://etherscan.io/address/0x8c1944fac705ef172f21f905b5523ae260f76d62</p>",
    "name_categories": "Exchange (DEX)",
    "token_name": "RUNE",
    "proof_archive_link": null,
    "technical_issue": null,
    "token_address": "0x3155ba85d5f96b2d030a4966af206230e46849cb",
    "token_addresses": [],
    "logo_link": "safe/files/scamDatabase/logo/611526c9dce57.jpeg",
    "date": "2021-7-22",
    "scam_updates": [],
    "proof_link": "https://medium.com/thorchain/post-mortem-eth-router-exploits-1-2-and-premature-return-to-trading-incident-2908928c5fb, https://www.rekt.news/thorchain-rekt2/",
    "website_link": "https://thorchain.org/",
    "webarchive_link": null,
    "twitter_link": "https://twitter.com/thorchain",
    "telegram_link": null,
    "our_post_link": null,
    "funds_lost": 8000000,
    "funds_returned": 0,
    "funds_by_chains": [],
    "funds_recovered": null,
    "active": 1,
    "git_hub": null,
    "git_hub_contract_link": null,
    "discord": null,
    "bug_bounty_program_link": null,
    "bug_bounty_program_company": null,
    "audit_code_conf": 0,
    "is_verified_source_code": 0,
    "is_public_team": 0,
    "scam_type": {
        "id": 19,
        "type": "Other"
    },
    "network": {},
    "scamNetworks": [
        {
            "networks_id": 1,
            "scam_database_id": 2553,
            "networks": {
                "id": 1,
                "name": "Ethereum",
                "icon_link": "safe/files/network/ethereum.png"
            }
        }
    ],
    "auditedBy": [
        {
            "audit_link": "safe/files/audit/pdf/THORChain_Final_Report.pdf",
            "date": "2020-04-06T00:00:00.000Z",
            "partner": {
                "id": 8,
                "name": "Certik",
                "logo_link": "safe/files/partner/logo/609520cbb1bba.png"
            }
        }
    ]
}