{
    "id": 2881,
    "project_name": "VinDAX",
    "title": "VinDAX",
    "description": "<p>VinDAX, a little-known cryptocurrency exchange in Vietnam, has been hacked, resulting in the loss of \"half a million USD\" in cryptocurrencies.<br><br>VinDAX has lost funds via 23 cryptocurrencies. The admin declined to share further information but said: \"We have made a full recovery from this attack,\" without providing details.</p>",
    "name_categories": "CeFi",
    "token_name": null,
    "proof_archive_link": null,
    "technical_issue": null,
    "token_address": null,
    "token_addresses": [],
    "logo_link": "safe/files/scamDatabase/logo/624481a554c23.jpeg",
    "date": "2019-11-8",
    "scam_updates": [],
    "proof_link": "https://bitcoinexchangeguide.com/vietnam-crypto-exchange-vindax-hacked-losing-500000-in-cryptocurrencies/",
    "website_link": "https://vindax.com/",
    "webarchive_link": null,
    "twitter_link": "https://twitter.com/VinDAXOfficial",
    "telegram_link": "https://t.me/VinDAX_Exchange",
    "our_post_link": null,
    "funds_lost": 500000,
    "funds_returned": 0,
    "funds_by_chains": [],
    "funds_recovered": null,
    "active": 1,
    "git_hub": null,
    "git_hub_contract_link": null,
    "discord": null,
    "bug_bounty_program_link": null,
    "bug_bounty_program_company": null,
    "audit_code_conf": null,
    "is_verified_source_code": 0,
    "is_public_team": 0,
    "scam_type": {
        "id": 19,
        "type": "Other"
    },
    "network": {},
    "scamNetworks": [
        {
            "networks_id": 1666600003,
            "scam_database_id": 2881,
            "networks": {
                "id": 1666600003,
                "name": "Centralized",
                "icon_link": "safe/files/network/cex.png"
            }
        }
    ],
    "auditedBy": []
}