{
    "id": 1610,
    "project_name": "Winnie-the-Pot",
    "title": "Winnie-the-Pot",
    "description": "<p>The contract owner could disable the transfer function, which restricted users in selling their tokens.<br><br></p>",
    "name_categories": "Token",
    "token_name": "WTP",
    "proof_archive_link": null,
    "technical_issue": null,
    "token_address": "0xd3380b47d76676ff77d4e3cc6c3fc51694d4f57b",
    "token_addresses": [],
    "logo_link": "safe/files/scamDatabase/logo/60f16dc37ab4d.png",
    "date": "2021-5-12",
    "scam_updates": [],
    "proof_link": "https://twitter.com/Token_Sniffer/status/1390015526294810624",
    "website_link": null,
    "webarchive_link": null,
    "twitter_link": null,
    "telegram_link": null,
    "our_post_link": null,
    "funds_lost": 0,
    "funds_returned": 0,
    "funds_by_chains": [],
    "funds_recovered": null,
    "active": 1,
    "git_hub": null,
    "git_hub_contract_link": null,
    "discord": null,
    "bug_bounty_program_link": null,
    "bug_bounty_program_company": null,
    "audit_code_conf": null,
    "is_verified_source_code": null,
    "is_public_team": null,
    "scam_type": {
        "id": 7,
        "type": "Honeypot"
    },
    "network": {},
    "scamNetworks": [
        {
            "networks_id": 56,
            "scam_database_id": 1610,
            "networks": {
                "id": 56,
                "name": "Binance",
                "icon_link": "safe/files/network/bsc.png"
            }
        }
    ],
    "auditedBy": []
}