{
    "id": 2568,
    "project_name": "Yoshi Defi",
    "title": "Yoshi Defi",
    "description": null,
    "name_categories": "Token",
    "token_name": "Yoshi Defi",
    "proof_archive_link": null,
    "technical_issue": null,
    "token_address": "0x76693A1EDc643855ce2d437a93666875481861aE",
    "token_addresses": [],
    "logo_link": "safe/files/scamDatabase/logo/61262eeab4a32.jpeg",
    "date": "2021-8-10",
    "scam_updates": [],
    "proof_link": "https://polygonscan.com/address/0x76693a1edc643855ce2d437a93666875481861ae#code",
    "website_link": "https://yoshi.polygonswaps.com/?__cf_chl_jschl_tk__=pmd_6bf92de70b918c36050fd11c85d13ed322fd48b0-1629110370-0-gqNtZGzNAc2jcnBszQjO",
    "webarchive_link": null,
    "twitter_link": null,
    "telegram_link": null,
    "our_post_link": null,
    "funds_lost": 0,
    "funds_returned": 0,
    "funds_by_chains": [],
    "funds_recovered": null,
    "active": 1,
    "git_hub": null,
    "git_hub_contract_link": null,
    "discord": null,
    "bug_bounty_program_link": null,
    "bug_bounty_program_company": null,
    "audit_code_conf": null,
    "is_verified_source_code": null,
    "is_public_team": null,
    "scam_type": {
        "id": 10,
        "type": "Rugpull"
    },
    "network": {},
    "scamNetworks": [
        {
            "networks_id": 137,
            "scam_database_id": 2568,
            "networks": {
                "id": 137,
                "name": "Polygon",
                "icon_link": "safe/files/network/polygon.png"
            }
        }
    ],
    "auditedBy": []
}